Workbook

Sheet Raw Data
A1: Row ID | B1: Order ID | C1: Order Date | D1: Clean Date | E1: Month | F1: Ship Date | G1: Ship Mode | H1: Customer ID | I1: Segment | J1: Country | K1: City | L1: State | M1: Region | N1: Product ID | O1: Category | P1: Sub-Category | Q1: Product Name | R1: Sales | S1: Quantity | T1: Discount | U1: Profit
A2: 1 | B2: CA-2016-152156 | C2: 42593 | D2: =IF(ISNUMBER(C2),C2,DATE(VALUE(RIGHT(C2,4)),VALUE(LEFT(C2,FIND("/",C2)-1)),VALUE(MID(C2,FIND("/",C2)+1,FIND("/",C2,FIND("/",C2)+1)-FIND("/",C2)-1)))) -> 42593 | E2: =D2 -> 42593 | F2: 42685 | G2: Second Class | H2: CG-12520 | I2: Consumer | J2: United States | K2: Henderson | L2: Kentucky | M2: South | N2: FUR-BO-10001798 | O2: Furniture | P2: Bookcases | Q2: Bush Somerset Collection Bookcase | R2: 261.96 | S2: 2 | T2: 0 | U2: 41.9136
A3: 2 | B3: CA-2016-152156 | C3: 42593 | D3: =IF(ISNUMBER(C3),C3,DATE(VALUE(RIGHT(C3,4)),VALUE(LEFT(C3,FIND("/",C3)-1)),VALUE(MID(C3,FIND("/",C3)+1,FIND("/",C3,FIND("/",C3)+1)-FIND("/",C3)-1)))) -> 42593 | E3: =D3 -> 42593 | F3: 42685 | G3: Second Class | H3: CG-12520 | I3: Consumer | J3: United States | K3: Henderson | L3: Kentucky | M3: South | N3: FUR-CH-10000454 | O3: Furniture | P3: Chairs | Q3: Hon Deluxe Fabric Upholstered Stacking Chairs, Rounded Back | R3: 731.94 | S3: 3 | T3: 0 | U3: 219.582
A4: 3 | B4: CA-2016-138688 | C4: 42710 | D4: =IF(ISNUMBER(C4),C4,DATE(VALUE(RIGHT(C4,4)),VALUE(LEFT(C4,FIND("/",C4)-1)),VALUE(MID(C4,FIND("/",C4)+1,FIND("/",C4,FIND("/",C4)+1)-FIND("/",C4)-1)))) -> 42710 | E4: =D4 -> 42710 | F4: 6/16/2016 | G4: Second Class | H4: DV-13045 | I4: Corporate | J4: United States | K4: Los Angeles | L4: California | M4: West | N4: OFF-LA-10000240 | O4: Office Supplies | P4: Labels | Q4: Self-Adhesive Address Labels for Typewriters by Universal | R4: 14.62 | S4: 2 | T4: 0 | U4: 6.8714
A5: 4 | B5: US-2015-108966 | C5: 42318 | D5: =IF(ISNUMBER(C5),C5,DATE(VALUE(RIGHT(C5,4)),VALUE(LEFT(C5,FIND("/",C5)-1)),VALUE(MID(C5,FIND("/",C5)+1,FIND("/",C5,FIND("/",C5)+1)-FIND("/",C5)-1)))) -> 42318 | E5: =D5 -> 42318 | F5: 10/18/2015 | G5: Standard Class | H5: SO-20335 | I5: Consumer | J5: United States | K5: Fort Lauderdale | L5: Florida | M5: South | N5: FUR-TA-10000577 | O5: Furniture | P5: Tables | Q5: Bretford CR4500 Series Slim Rectangular Table | R5: 957.5775 | S5: 5 | T5: 0.45 | U5: -383.031
A6: 5 | B6: US-2015-108966 | C6: 42318 | D6: =IF(ISNUMBER(C6),C6,DATE(VALUE(RIGHT(C6,4)),VALUE(LEFT(C6,FIND("/",C6)-1)),VALUE(MID(C6,FIND("/",C6)+1,FIND("/",C6,FIND("/",C6)+1)-FIND("/",C6)-1)))) -> 42318 | E6: =D6 -> 42318 | F6: 10/18/2015 | G6: Standard Class | H6: SO-20335 | I6: Consumer | J6: United States | K6: Fort Lauderdale | L6: Florida | M6: South | N6: OFF-ST-10000760 | O6: Office Supplies | P6: Storage | Q6: Eldon Fold 'N Roll Cart System | R6: 22.368 | S6: 2 | T6: 0.2 | U6: 2.5164
A7: 6 | B7: CA-2014-115812 | C7: 41888 | D7: =IF(ISNUMBER(C7),C7,DATE(VALUE(RIGHT(C7,4)),VALUE(LEFT(C7,FIND("/",C7)-1)),VALUE(MID(C7,FIND("/",C7)+1,FIND("/",C7,FIND("/",C7)+1)-FIND("/",C7)-1)))) -> 41888 | E7: =D7 -> 41888 | F7: 6/14/2014 | G7: Standard Class | H7: BH-11710 | I7: Consumer | J7: United States | K7: Los Angeles | L7: California | M7: West | N7: FUR-FU-10001487 | O7: Furniture | P7: Furnishings | Q7: Eldon Expressions Wood and Plastic Desk Accessories, Cherry Wood | R7: 48.86 | S7: 7 | T7: 0 | U7: 14.1694
A8: 7 | B8: CA-2014-115812 | C8: 41888 | D8: =IF(ISNUMBER(C8),C8,DATE(VALUE(RIGHT(C8,4)),VALUE(LEFT(C8,FIND("/",C8)-1)),VALUE(MID(C8,FIND("/",C8)+1,FIND("/",C8,FIND("/",C8)+1)-FIND("/",C8)-1)))) -> 41888 | E8: =D8 -> 41888 | F8: 6/14/2014 | G8: Standard Class | H8: BH-11710 | I8: Consumer | J8: United States | K8: Los Angeles | L8: California | M8: West | N8: OFF-AR-10002833 | O8: Office Supplies | P8: Art | Q8: Newell 322 | R8: 7.28 | S8: 4 | T8: 0 | U8: 1.9656
A9: 8 | B9: CA-2014-115812 | C9: 41888 | D9: =IF(ISNUMBER(C9),C9,DATE(VALUE(RIGHT(C9,4)),VALUE(LEFT(C9,FIND("/",C9)-1)),VALUE(MID(C9,FIND("/",C9)+1,FIND("/",C9,FIND("/",C9)+1)-FIND("/",C9)-1)))) -> 41888 | E9: =D9 -> 41888 | F9: 6/14/2014 | G9: Standard Class | H9: BH-11710 | I9: Consumer | J9: United States | K9: Los Angeles | L9: California | M9: West | N9: TEC-PH-10002275 | O9: Technology | P9: Phones | Q9: Mitel 5320 IP Phone VoIP phone | R9: 907.152 | S9: 6 | T9: 0.2 | U9: 90.7152 | X9: =ISNUMBER(C16) -> FALSE
A10: 9 | B10: CA-2014-115812 | C10: 41888 | D10: =IF(ISNUMBER(C10),C10,DATE(VALUE(RIGHT(C10,4)),VALUE(LEFT(C10,FIND("/",C10)-1)),VALUE(MID(C10,FIND("/",C10)+1,FIND("/",C10,FIND("/",C10)+1)-FIND("/",C10)-1)))) -> 41888 | E10: =D10 -> 41888 | F10: 6/14/2014 | G10: Standard Class | H10: BH-11710 | I10: Consumer | J10: United States | K10: Los Angeles | L10: California | M10: West | N10: OFF-BI-10003910 | O10: Office Supplies | P10: Binders | Q10: DXL Angle-View Binders with Locking Rings by Samsill | R10: 18.504 | S10: 3 | T10: 0.2 | U10: 5.7825
A11: 10 | B11: CA-2014-115812 | C11: 41888 | D11: =IF(ISNUMBER(C11),C11,DATE(VALUE(RIGHT(C11,4)),VALUE(LEFT(C11,FIND("/",C11)-1)),VALUE(MID(C11,FIND("/",C11)+1,FIND("/",C11,FIND("/",C11)+1)-FIND("/",C11)-1)))) -> 41888 | E11: =D11 -> 41888 | F11: 6/14/2014 | G11: Standard Class | H11: BH-11710 | I11: Consumer | J11: United States | K11: Los Angeles | L11: California | M11: West | N11: OFF-AP-10002892 | O11: Office Supplies | P11: Appliances | Q11: Belkin F5C206VTEL 6 Outlet Surge | R11: 114.9 | S11: 5 | T11: 0 | U11: 34.47
A12: 11 | B12: CA-2014-115812 | C12: 41888 | D12: =IF(ISNUMBER(C12),C12,DATE(VALUE(RIGHT(C12,4)),VALUE(LEFT(C12,FIND("/",C12)-1)),VALUE(MID(C12,FIND("/",C12)+1,FIND("/",C12,FIND("/",C12)+1)-FIND("/",C12)-1)))) -> 41888 | E12: =D12 -> 41888 | F12: 6/14/2014 | G12: Standard Class | H12: BH-11710 | I12: Consumer | J12: United States | K12: Los Angeles | L12: California | M12: West | N12: FUR-TA-10001539 | O12: Furniture | P12: Tables | Q12: Chromcraft Rectangular Conference Tables | R12: 1706.184 | S12: 9 | T12: 0.2 | U12: 85.3092
A13: 12 | B13: CA-2014-115812 | C13: 41888 | D13: =IF(ISNUMBER(C13),C13,DATE(VALUE(RIGHT(C13,4)),VALUE(LEFT(C13,FIND("/",C13)-1)),VALUE(MID(C13,FIND("/",C13)+1,FIND("/",C13,FIND("/",C13)+1)-FIND("/",C13)-1)))) -> 41888 | E13: =D13 -> 41888 | F13: 6/14/2014 | G13: Standard Class | H13: BH-11710 | I13: Consumer | J13: United States | K13: Los Angeles | L13: California | M13: West | N13: TEC-PH-10002033 | O13: Technology | P13: Phones | Q13: Konftel 250 ConferenceÂ phoneÂ - Charcoal black | R13: 911.424 | S13: 4 | T13: 0.2 | U13: 68.3568
A14: 13 | B14: CA-2017-114412 | C14: 4/15/2017 | D14: =IF(ISNUMBER(C14),C14,DATE(VALUE(RIGHT(C14,4)),VALUE(LEFT(C14,FIND("/",C14)-1)),VALUE(MID(C14,FIND("/",C14)+1,FIND("/",C14,FIND("/",C14)+1)-FIND("/",C14)-1)))) -> 42840 | E14: =D14 -> 42840 | F14: 4/20/2017 | G14: Standard Class | H14: AA-10480 | I14: Consumer | J14: United States | K14: Concord | L14: North Carolina | M14: South | N14: OFF-PA-10002365 | O14: Office Supplies | P14: Paper | Q14: Xerox 1967 | R14: 15.552 | S14: 3 | T14: 0.2 | U14: 5.4432
A15: 14 | B15: CA-2016-161389 | C15: 42502 | D15: =IF(ISNUMBER(C15),C15,DATE(VALUE(RIGHT(C15,4)),VALUE(LEFT(C15,FIND("/",C15)-1)),VALUE(MID(C15,FIND("/",C15)+1,FIND("/",C15,FIND("/",C15)+1)-FIND("/",C15)-1)))) -> 42502 | E15: =D15 -> 42502 | F15: 42655 | G15: Standard Class | H15: IM-15070 | I15: Consumer | J15: United States | K15: Seattle | L15: Washington | M15: West | N15: OFF-BI-10003656 | O15: Office Supplies | P15: Binders | Q15: Fellowes PB200 Plastic Comb Binding Machine | R15: 407.976 | S15: 3 | T15: 0.2 | U15: 132.5922
A16: 15 | B16: US-2015-118983 | C16: 11/22/2015 | D16: =IF(ISNUMBER(C16),C16,DATE(VALUE(RIGHT(C16,4)),VALUE(LEFT(C16,FIND("/",C16)-1)),VALUE(MID(C16,FIND("/",C16)+1,FIND("/",C16,FIND("/",C16)+1)-FIND("/",C16)-1)))) -> 42330 | E16: =D16 -> 42330 | F16: 11/26/2015 | G16: Standard Class | H16: HP-14815 | I16: Home Office | J16: United States | K16: Fort Worth | L16: Texas | M16: Central | N16: OFF-AP-10002311 | O16: Office Supplies | P16: Appliances | Q16: Holmes Replacement Filter for HEPA Air Cleaner, Very Large Room, HEPA Filter | R16: 68.81 | S16: 5 | T16: 0.8 | U16: -123.858
A17: 16 | B17: US-2015-118983 | C17: 11/22/2015 | D17: =IF(ISNUMBER(C17),C17,DATE(VALUE(RIGHT(C17,4)),VALUE(LEFT(C17,FIND("/",C17)-1)),VALUE(MID(C17,FIND("/",C17)+1,FIND("/",C17,FIND("/",C17)+1)-FIND("/",C17)-1)))) -> 42330 | E17: =D17 -> 42330 | F17: 11/26/2015 | G17: Standard Class | H17: HP-14815 | I17: Home Office | J17: United States | K17: Fort Worth | L17: Texas | M17: Central | N17: OFF-BI-10000756 | O17: Office Supplies | P17: Binders | Q17: Storex DuraTech Recycled Plastic Frosted Binders | R17: 2.544 | S17: 3 | T17: 0.8 | U17: -3.816
A18: 17 | B18: CA-2014-105893 | C18: 41954 | D18: =IF(ISNUMBER(C18),C18,DATE(VALUE(RIGHT(C18,4)),VALUE(LEFT(C18,FIND("/",C18)-1)),VALUE(MID(C18,FIND("/",C18)+1,FIND("/",C18,FIND("/",C18)+1)-FIND("/",C18)-1)))) -> 41954 | E18: =D18 -> 41954 | F18: 11/18/2014 | G18: Standard Class | H18: PK-19075 | I18: Consumer | J18: United States | K18: Madison | L18: Wisconsin | M18: Central | N18: OFF-ST-10004186 | O18: Office Supplies | P18: Storage | Q18: Stur-D-Stor Shelving, Vertical 5-Shelf: 72"H x 36"W x 18 1/2"D | R18: 665.88 | S18: 6 | T18: 0 | U18: 13.3176
A19: 18 | B19: CA-2014-167164 | C19: 5/13/2014 | D19: =IF(ISNUMBER(C19),C19,DATE(VALUE(RIGHT(C19,4)),VALUE(LEFT(C19,FIND("/",C19)-1)),VALUE(MID(C19,FIND("/",C19)+1,FIND("/",C19,FIND("/",C19)+1)-FIND("/",C19)-1)))) -> 41772 | E19: =D19 -> 41772 | F19: 5/15/2014 | G19: Second Class | H19: AG-10270 | I19: Consumer | J19: United States | K19: West Jordan | L19: Utah | M19: West | N19: OFF-ST-10000107 | O19: Office Supplies | P19: Storage | Q19: Fellowes Super Stor/Drawer | R19: 55.5 | S19: 2 | T19: 0 | U19: 9.99
A20: 19 | B20: CA-2014-143336 | C20: 8/27/2014 | D20: =IF(ISNUMBER(C20),C20,DATE(VALUE(RIGHT(C20,4)),VALUE(LEFT(C20,FIND("/",C20)-1)),VALUE(MID(C20,FIND("/",C20)+1,FIND("/",C20,FIND("/",C20)+1)-FIND("/",C20)-1)))) -> 41878 | E20: =D20 -> 41878 | F20: 41648 | G20: Second Class | H20: ZD-21925 | I20: Consumer | J20: United States | K20: San Francisco | L20: California | M20: West | N20: OFF-AR-10003056 | O20: Office Supplies | P20: Art | Q20: Newell 341 | R20: 8.56 | S20: 2 | T20: 0 | U20: 2.4824
A21: 20 | B21: CA-2014-143336 | C21: 8/27/2014 | D21: =IF(ISNUMBER(C21),C21,DATE(VALUE(RIGHT(C21,4)),VALUE(LEFT(C21,FIND("/",C21)-1)),VALUE(MID(C21,FIND("/",C21)+1,FIND("/",C21,FIND("/",C21)+1)-FIND("/",C21)-1)))) -> 41878 | E21: =D21 -> 41878 | F21: 41648 | G21: Second Class | H21: ZD-21925 | I21: Consumer | J21: United States | K21: San Francisco | L21: California | M21: West | N21: TEC-PH-10001949 | O21: Technology | P21: Phones | Q21: Cisco SPA 501G IP Phone | R21: 213.48 | S21: 3 | T21: 0.2 | U21: 16.011
A22: 21 | B22: CA-2014-143336 | C22: 8/27/2014 | D22: =IF(ISNUMBER(C22),C22,DATE(VALUE(RIGHT(C22,4)),VALUE(LEFT(C22,FIND("/",C22)-1)),VALUE(MID(C22,FIND("/",C22)+1,FIND("/",C22,FIND("/",C22)+1)-FIND("/",C22)-1)))) -> 41878 | E22: =D22 -> 41878 | F22: 41648 | G22: Second Class | H22: ZD-21925 | I22: Consumer | J22: United States | K22: San Francisco | L22: California | M22: West | N22: OFF-BI-10002215 | O22: Office Supplies | P22: Binders | Q22: Wilson Jones Hanging View Binder, White, 1" | R22: 22.72 | S22: 4 | T22: 0.2 | U22: 7.384
A23: 22 | B23: CA-2016-137330 | C23: 42625 | D23: =IF(ISNUMBER(C23),C23,DATE(VALUE(RIGHT(C23,4)),VALUE(LEFT(C23,FIND("/",C23)-1)),VALUE(MID(C23,FIND("/",C23)+1,FIND("/",C23,FIND("/",C23)+1)-FIND("/",C23)-1)))) -> 42625 | E23: =D23 -> 42625 | F23: 12/13/2016 | G23: Standard Class | H23: KB-16585 | I23: Corporate | J23: United States | K23: Fremont | L23: Nebraska | M23: Central | N23: OFF-AR-10000246 | O23: Office Supplies | P23: Art | Q23: Newell 318 | R23: 19.46 | S23: 7 | T23: 0 | U23: 5.0596
A24: 23 | B24: CA-2016-137330 | C24: 42625 | D24: =IF(ISNUMBER(C24),C24,DATE(VALUE(RIGHT(C24,4)),VALUE(LEFT(C24,FIND("/",C24)-1)),VALUE(MID(C24,FIND("/",C24)+1,FIND("/",C24,FIND("/",C24)+1)-FIND("/",C24)-1)))) -> 42625 | E24: =D24 -> 42625 | F24: 12/13/2016 | G24: Standard Class | H24: KB-16585 | I24: Corporate | J24: United States | K24: Fremont | L24: Nebraska | M24: Central | N24: OFF-AP-10001492 | O24: Office Supplies | P24: Appliances | Q24: Acco Six-Outlet Power Strip, 4' Cord Length | R24: 60.34 | S24: 7 | T24: 0 | U24: 15.6884
A25: 24 | B25: US-2017-156909 | C25: 7/16/2017 | D25: =IF(ISNUMBER(C25),C25,DATE(VALUE(RIGHT(C25,4)),VALUE(LEFT(C25,FIND("/",C25)-1)),VALUE(MID(C25,FIND("/",C25)+1,FIND("/",C25,FIND("/",C25)+1)-FIND("/",C25)-1)))) -> 42932 | E25: =D25 -> 42932 | F25: 7/18/2017 | G25: Second Class | H25: SF-20065 | I25: Consumer | J25: United States | K25: Philadelphia | L25: Pennsylvania | M25: East | N25: FUR-CH-10002774 | O25: Furniture | P25: Chairs | Q25: Global Deluxe Stacking Chair, Gray | R25: 71.372 | S25: 2 | T25: 0.3 | U25: -1.0196
A26: 25 | B26: CA-2015-106320 | C26: 9/25/2015 | D26: =IF(ISNUMBER(C26),C26,DATE(VALUE(RIGHT(C26,4)),VALUE(LEFT(C26,FIND("/",C26)-1)),VALUE(MID(C26,FIND("/",C26)+1,FIND("/",C26,FIND("/",C26)+1)-FIND("/",C26)-1)))) -> 42272 | E26: =D26 -> 42272 | F26: 9/30/2015 | G26: Standard Class | H26: EB-13870 | I26: Consumer | J26: United States | K26: Orem | L26: Utah | M26: West | N26: FUR-TA-10000577 | O26: Furniture | P26: Tables | Q26: Bretford CR4500 Series Slim Rectangular Table | R26: 1044.63 | S26: 3 | T26: 0 | U26: 240.2649
A27: 26 | B27: CA-2016-121755 | C27: 1/16/2016 | D27: =IF(ISNUMBER(C27),C27,DATE(VALUE(RIGHT(C27,4)),VALUE(LEFT(C27,FIND("/",C27)-1)),VALUE(MID(C27,FIND("/",C27)+1,FIND("/",C27,FIND("/",C27)+1)-FIND("/",C27)-1)))) -> 42385 | E27: =D27 -> 42385 | F27: 1/20/2016 | G27: Second Class | H27: EH-13945 | I27: Consumer | J27: United States | K27: Los Angeles | L27: California | M27: West | N27: OFF-BI-10001634 | O27: Office Supplies | P27: Binders | Q27: Wilson Jones Active Use Binders | R27: 11.648 | S27: 2 | T27: 0.2 | U27: 4.2224
A28: 27 | B28: CA-2016-121755 | C28: 1/16/2016 | D28: =IF(ISNUMBER(C28),C28,DATE(VALUE(RIGHT(C28,4)),VALUE(LEFT(C28,FIND("/",C28)-1)),VALUE(MID(C28,FIND("/",C28)+1,FIND("/",C28,FIND("/",C28)+1)-FIND("/",C28)-1)))) -> 42385 | E28: =D28 -> 42385 | F28: 1/20/2016 | G28: Second Class | H28: EH-13945 | I28: Consumer | J28: United States | K28: Los Angeles | L28: California | M28: West | N28: TEC-AC-10003027 | O28: Technology | P28: Accessories | Q28: ImationÂ 8GB Mini TravelDrive USB 2.0Â Flash Drive | R28: 90.57 | S28: 3 | T28: 0 | U28: 11.7741
A29: 28 | B29: US-2015-150630 | C29: 9/17/2015 | D29: =IF(ISNUMBER(C29),C29,DATE(VALUE(RIGHT(C29,4)),VALUE(LEFT(C29,FIND("/",C29)-1)),VALUE(MID(C29,FIND("/",C29)+1,FIND("/",C29,FIND("/",C29)+1)-FIND("/",C29)-1)))) -> 42264 | E29: =D29 -> 42264 | F29: 9/21/2015 | G29: Standard Class | H29: TB-21520 | I29: Consumer | J29: United States | K29: Philadelphia | L29: Pennsylvania | M29: East | N29: FUR-BO-10004834 | O29: Furniture | P29: Bookcases | Q29: Riverside Palais Royal Lawyers Bookcase, Royale Cherry Finish | R29: 3083.43 | S29: 7 | T29: 0.5 | U29: -1665.0522
A30: 29 | B30: US-2015-150630 | C30: 9/17/2015 | D30: =IF(ISNUMBER(C30),C30,DATE(VALUE(RIGHT(C30,4)),VALUE(LEFT(C30,FIND("/",C30)-1)),VALUE(MID(C30,FIND("/",C30)+1,FIND("/",C30,FIND("/",C30)+1)-FIND("/",C30)-1)))) -> 42264 | E30: =D30 -> 42264 | F30: 9/21/2015 | G30: Standard Class | H30: TB-21520 | I30: Consumer | J30: United States | K30: Philadelphia | L30: Pennsylvania | M30: East | N30: OFF-BI-10000474 | O30: Office Supplies | P30: Binders | Q30: Avery Recycled Flexi-View Covers for Binding Systems | R30: 9.618 | S30: 2 | T30: 0.7 | U30: -7.0532
A31: 30 | B31: US-2015-150630 | C31: 9/17/2015 | D31: =IF(ISNUMBER(C31),C31,DATE(VALUE(RIGHT(C31,4)),VALUE(LEFT(C31,FIND("/",C31)-1)),VALUE(MID(C31,FIND("/",C31)+1,FIND("/",C31,FIND("/",C31)+1)-FIND("/",C31)-1)))) -> 42264 | E31: =D31 -> 42264 | F31: 9/21/2015 | G31: Standard Class | H31: TB-21520 | I31: Consumer | J31: United States | K31: Philadelphia | L31: Pennsylvania | M31: East | N31: FUR-FU-10004848 | O31: Furniture | P31: Furnishings | Q31: Howard Miller 13-3/4" Diameter Brushed Chrome Round Wall Clock | R31: 124.2 | S31: 3 | T31: 0.2 | U31: 15.525
A32: 31 | B32: US-2015-150630 | C32: 9/17/2015 | D32: =IF(ISNUMBER(C32),C32,DATE(VALUE(RIGHT(C32,4)),VALUE(LEFT(C32,FIND("/",C32)-1)),VALUE(MID(C32,FIND("/",C32)+1,FIND("/",C32,FIND("/",C32)+1)-FIND("/",C32)-1)))) -> 42264 | E32: =D32 -> 42264 | F32: 9/21/2015 | G32: Standard Class | H32: TB-21520 | I32: Consumer | J32: United States | K32: Philadelphia | L32: Pennsylvania | M32: East | N32: OFF-EN-10001509 | O32: Office Supplies | P32: Envelopes | Q32: Poly String Tie Envelopes | R32: 3.264 | S32: 2 | T32: 0.2 | U32: 1.1016
A33: 32 | B33: US-2015-150630 | C33: 9/17/2015 | D33: =IF(ISNUMBER(C33),C33,DATE(VALUE(RIGHT(C33,4)),VALUE(LEFT(C33,FIND("/",C33)-1)),VALUE(MID(C33,FIND("/",C33)+1,FIND("/",C33,FIND("/",C33)+1)-FIND("/",C33)-1)))) -> 42264 | E33: =D33 -> 42264 | F33: 9/21/2015 | G33: Standard Class | H33: TB-21520 | I33: Consumer | J33: United States | K33: Philadelphia | L33: Pennsylvania | M33: East | N33: OFF-AR-10004042 | O33: Office Supplies | P33: Art | Q33: BOSTON Model 1800 Electric Pencil Sharpeners, Putty/Woodgrain | R33: 86.304 | S33: 6 | T33: 0.2 | U33: 9.7092
A34: 33 | B34: US-2015-150630 | C34: 9/17/2015 | D34: =IF(ISNUMBER(C34),C34,DATE(VALUE(RIGHT(C34,4)),VALUE(LEFT(C34,FIND("/",C34)-1)),VALUE(MID(C34,FIND("/",C34)+1,FIND("/",C34,FIND("/",C34)+1)-FIND("/",C34)-1)))) -> 42264 | E34: =D34 -> 42264 | F34: 9/21/2015 | G34: Standard Class | H34: TB-21520 | I34: Consumer | J34: United States | K34: Philadelphia | L34: Pennsylvania | M34: East | N34: OFF-BI-10001525 | O34: Office Supplies | P34: Binders | Q34: Acco Pressboard Covers with Storage Hooks, 14 7/8" x 11", Executive Red | R34: 6.858 | S34: 6 | T34: 0.7 | U34: -5.715
A35: 34 | B35: US-2015-150630 | C35: 9/17/2015 | D35: =IF(ISNUMBER(C35),C35,DATE(VALUE(RIGHT(C35,4)),VALUE(LEFT(C35,FIND("/",C35)-1)),VALUE(MID(C35,FIND("/",C35)+1,FIND("/",C35,FIND("/",C35)+1)-FIND("/",C35)-1)))) -> 42264 | E35: =D35 -> 42264 | F35: 9/21/2015 | G35: Standard Class | H35: TB-21520 | I35: Consumer | J35: United States | K35: Philadelphia | L35: Pennsylvania | M35: East | N35: OFF-AR-10001683 | O35: Office Supplies | P35: Art | Q35: Lumber Crayons | R35: 15.76 | S35: 2 | T35: 0.2 | U35: 3.546
A36: 35 | B36: CA-2017-107727 | C36: 10/19/2017 | D36: =IF(ISNUMBER(C36),C36,DATE(VALUE(RIGHT(C36,4)),VALUE(LEFT(C36,FIND("/",C36)-1)),VALUE(MID(C36,FIND("/",C36)+1,FIND("/",C36,FIND("/",C36)+1)-FIND("/",C36)-1)))) -> 43027 | E36: =D36 -> 43027 | F36: 10/23/2017 | G36: Second Class | H36: MA-17560 | I36: Home Office | J36: United States | K36: Houston | L36: Texas | M36: Central | N36: OFF-PA-10000249 | O36: Office Supplies | P36: Paper | Q36: Easy-staple paper | R36: 29.472 | S36: 3 | T36: 0.2 | U36: 9.9468
A37: 36 | B37: CA-2016-117590 | C37: 42594 | D37: =IF(ISNUMBER(C37),C37,DATE(VALUE(RIGHT(C37,4)),VALUE(LEFT(C37,FIND("/",C37)-1)),VALUE(MID(C37,FIND("/",C37)+1,FIND("/",C37,FIND("/",C37)+1)-FIND("/",C37)-1)))) -> 42594 | E37: =D37 -> 42594 | F37: 42655 | G37: First Class | H37: GH-14485 | I37: Corporate | J37: United States | K37: Richardson | L37: Texas | M37: Central | N37: TEC-PH-10004977 | O37: Technology | P37: Phones | Q37: GE 30524EE4 | R37: 1097.544 | S37: 7 | T37: 0.2 | U37: 123.4737
A38: 37 | B38: CA-2016-117590 | C38: 42594 | D38: =IF(ISNUMBER(C38),C38,DATE(VALUE(RIGHT(C38,4)),VALUE(LEFT(C38,FIND("/",C38)-1)),VALUE(MID(C38,FIND("/",C38)+1,FIND("/",C38,FIND("/",C38)+1)-FIND("/",C38)-1)))) -> 42594 | E38: =D38 -> 42594 | F38: 42655 | G38: First Class | H38: GH-14485 | I38: Corporate | J38: United States | K38: Richardson | L38: Texas | M38: Central | N38: FUR-FU-10003664 | O38: Furniture | P38: Furnishings | Q38: Electrix Architect's Clamp-On Swing Arm Lamp, Black | R38: 190.92 | S38: 5 | T38: 0.6 | U38: -147.963
A39: 38 | B39: CA-2015-117415 | C39: 12/27/2015 | D39: =IF(ISNUMBER(C39),C39,DATE(VALUE(RIGHT(C39,4)),VALUE(LEFT(C39,FIND("/",C39)-1)),VALUE(MID(C39,FIND("/",C39)+1,FIND("/",C39,FIND("/",C39)+1)-FIND("/",C39)-1)))) -> 42365 | E39: =D39 -> 42365 | F39: 12/31/2015 | G39: Standard Class | H39: SN-20710 | I39: Home Office | J39: United States | K39: Houston | L39: Texas | M39: Central | N39: OFF-EN-10002986 | O39: Office Supplies | P39: Envelopes | Q39: #10-4 1/8" x 9 1/2" Premium Diagonal Seam Envelopes | R39: 113.328 | S39: 9 | T39: 0.2 | U39: 35.415
A40: 39 | B40: CA-2015-117415 | C40: 12/27/2015 | D40: =IF(ISNUMBER(C40),C40,DATE(VALUE(RIGHT(C40,4)),VALUE(LEFT(C40,FIND("/",C40)-1)),VALUE(MID(C40,FIND("/",C40)+1,FIND("/",C40,FIND("/",C40)+1)-FIND("/",C40)-1)))) -> 42365 | E40: =D40 -> 42365 | F40: 12/31/2015 | G40: Standard Class | H40: SN-20710 | I40: Home Office | J40: United States | K40: Houston | L40: Texas | M40: Central | N40: FUR-BO-10002545 | O40: Furniture | P40: Bookcases | Q40: Atlantic Metals Mobile 3-Shelf Bookcases, Custom Colors | R40: 532.3992 | S40: 3 | T40: 0.32 | U40: -46.9764
A41: 40 | B41: CA-2015-117415 | C41: 12/27/2015 | D41: =IF(ISNUMBER(C41),C41,DATE(VALUE(RIGHT(C41,4)),VALUE(LEFT(C41,FIND("/",C41)-1)),VALUE(MID(C41,FIND("/",C41)+1,FIND("/",C41,FIND("/",C41)+1)-FIND("/",C41)-1)))) -> 42365 | E41: =D41 -> 42365 | F41: 12/31/2015 | G41: Standard Class | H41: SN-20710 | I41: Home Office | J41: United States | K41: Houston | L41: Texas | M41: Central | N41: FUR-CH-10004218 | O41: Furniture | P41: Chairs | Q41: Global Fabric Manager's Chair, Dark Gray | R41: 212.058 | S41: 3 | T41: 0.3 | U41: -15.147
A42: 41 | B42: CA-2015-117415 | C42: 12/27/2015 | D42: =IF(ISNUMBER(C42),C42,DATE(VALUE(RIGHT(C42,4)),VALUE(LEFT(C42,FIND("/",C42)-1)),VALUE(MID(C42,FIND("/",C42)+1,FIND("/",C42,FIND("/",C42)+1)-FIND("/",C42)-1)))) -> 42365 | E42: =D42 -> 42365 | F42: 12/31/2015 | G42: Standard Class | H42: SN-20710 | I42: Home Office | J42: United States | K42: Houston | L42: Texas | M42: Central | N42: TEC-PH-10000486 | O42: Technology | P42: Phones | Q42: Plantronics HL10 Handset Lifter | R42: 371.168 | S42: 4 | T42: 0.2 | U42: 41.7564
A43: 42 | B43: CA-2017-120999 | C43: 43017 | D43: =IF(ISNUMBER(C43),C43,DATE(VALUE(RIGHT(C43,4)),VALUE(LEFT(C43,FIND("/",C43)-1)),VALUE(MID(C43,FIND("/",C43)+1,FIND("/",C43,FIND("/",C43)+1)-FIND("/",C43)-1)))) -> 43017 | E43: =D43 -> 43017 | F43: 9/15/2017 | G43: Standard Class | H43: LC-16930 | I43: Corporate | J43: United States | K43: Naperville | L43: Illinois | M43: Central | N43: TEC-PH-10004093 | O43: Technology | P43: Phones | Q43: Panasonic Kx-TS550 | R43: 147.168 | S43: 4 | T43: 0.2 | U43: 16.5564
A44: 43 | B44: CA-2016-101343 | C44: 7/17/2016 | D44: =IF(ISNUMBER(C44),C44,DATE(VALUE(RIGHT(C44,4)),VALUE(LEFT(C44,FIND("/",C44)-1)),VALUE(MID(C44,FIND("/",C44)+1,FIND("/",C44,FIND("/",C44)+1)-FIND("/",C44)-1)))) -> 42568 | E44: =D44 -> 42568 | F44: 7/22/2016 | G44: Standard Class | H44: RA-19885 | I44: Corporate | J44: United States | K44: Los Angeles | L44: California | M44: West | N44: OFF-ST-10003479 | O44: Office Supplies | P44: Storage | Q44: Eldon Base for stackable storage shelf, platinum | R44: 77.88 | S44: 2 | T44: 0 | U44: 3.894
A45: 44 | B45: CA-2017-139619 | C45: 9/19/2017 | D45: =IF(ISNUMBER(C45),C45,DATE(VALUE(RIGHT(C45,4)),VALUE(LEFT(C45,FIND("/",C45)-1)),VALUE(MID(C45,FIND("/",C45)+1,FIND("/",C45,FIND("/",C45)+1)-FIND("/",C45)-1)))) -> 42997 | E45: =D45 -> 42997 | F45: 9/23/2017 | G45: Standard Class | H45: ES-14080 | I45: Corporate | J45: United States | K45: Melbourne | L45: Florida | M45: South | N45: OFF-ST-10003282 | O45: Office Supplies | P45: Storage | Q45: Advantus 10-Drawer Portable Organizer, Chrome Metal Frame, Smoke Drawers | R45: 95.616 | S45: 2 | T45: 0.2 | U45: 9.5616
A46: 45 | B46: CA-2016-118255 | C46: 42677 | D46: =IF(ISNUMBER(C46),C46,DATE(VALUE(RIGHT(C46,4)),VALUE(LEFT(C46,FIND("/",C46)-1)),VALUE(MID(C46,FIND("/",C46)+1,FIND("/",C46,FIND("/",C46)+1)-FIND("/",C46)-1)))) -> 42677 | E46: =D46 -> 42677 | F46: 3/13/2016 | G46: First Class | H46: ON-18715 | I46: Corporate | J46: United States | K46: Eagan | L46: Minnesota | M46: Central | N46: TEC-AC-10000171 | O46: Technology | P46: Accessories | Q46: Verbatim 25 GB 6x Blu-ray Single Layer Recordable Disc, 25/Pack | R46: 45.98 | S46: 2 | T46: 0 | U46: 19.7714
A47: 46 | B47: CA-2016-118255 | C47: 42677 | D47: =IF(ISNUMBER(C47),C47,DATE(VALUE(RIGHT(C47,4)),VALUE(LEFT(C47,FIND("/",C47)-1)),VALUE(MID(C47,FIND("/",C47)+1,FIND("/",C47,FIND("/",C47)+1)-FIND("/",C47)-1)))) -> 42677 | E47: =D47 -> 42677 | F47: 3/13/2016 | G47: First Class | H47: ON-18715 | I47: Corporate | J47: United States | K47: Eagan | L47: Minnesota | M47: Central | N47: OFF-BI-10003291 | O47: Office Supplies | P47: Binders | Q47: Wilson Jones Leather-Like Binders with DublLock Round Rings | R47: 17.46 | S47: 2 | T47: 0 | U47: 8.2062
A48: 47 | B48: CA-2014-146703 | C48: 10/20/2014 | D48: =IF(ISNUMBER(C48),C48,DATE(VALUE(RIGHT(C48,4)),VALUE(LEFT(C48,FIND("/",C48)-1)),VALUE(MID(C48,FIND("/",C48)+1,FIND("/",C48,FIND("/",C48)+1)-FIND("/",C48)-1)))) -> 41932 | E48: =D48 -> 41932 | F48: 10/25/2014 | G48: Second Class | H48: PO-18865 | I48: Consumer | J48: United States | K48: Westland | L48: Michigan | M48: Central | N48: OFF-ST-10001713 | O48: Office Supplies | P48: Storage | Q48: Gould Plastics 9-Pocket Panel Bin, 18-3/8w x 5-1/4d x 20-1/2h, Black | R48: 211.96 | S48: 4 | T48: 0 | U48: 8.4784
A49: 48 | B49: CA-2016-169194 | C49: 6/20/2016 | D49: =IF(ISNUMBER(C49),C49,DATE(VALUE(RIGHT(C49,4)),VALUE(LEFT(C49,FIND("/",C49)-1)),VALUE(MID(C49,FIND("/",C49)+1,FIND("/",C49,FIND("/",C49)+1)-FIND("/",C49)-1)))) -> 42541 | E49: =D49 -> 42541 | F49: 6/25/2016 | G49: Standard Class | H49: LH-16900 | I49: Consumer | J49: United States | K49: Dover | L49: Delaware | M49: East | N49: TEC-AC-10002167 | O49: Technology | P49: Accessories | Q49: ImationÂ 8gb Micro Traveldrive Usb 2.0Â Flash Drive | R49: 45 | S49: 3 | T49: 0 | U49: 4.95
A50: 49 | B50: CA-2016-169194 | C50: 6/20/2016 | D50: =IF(ISNUMBER(C50),C50,DATE(VALUE(RIGHT(C50,4)),VALUE(LEFT(C50,FIND("/",C50)-1)),VALUE(MID(C50,FIND("/",C50)+1,FIND("/",C50,FIND("/",C50)+1)-FIND("/",C50)-1)))) -> 42541 | E50: =D50 -> 42541 | F50: 6/25/2016 | G50: Standard Class | H50: LH-16900 | I50: Consumer | J50: United States | K50: Dover | L50: Delaware | M50: East | N50: TEC-PH-10003988 | O50: Technology | P50: Phones | Q50: LF Elite 3D Dazzle Designer Hard Case Cover, Lf Stylus Pen and Wiper For Apple Iphone 5c Mini Lite | R50: 21.8 | S50: 2 | T50: 0 | U50: 6.104
A51: 50 | B51: CA-2015-115742 | C51: 4/18/2015 | D51: =IF(ISNUMBER(C51),C51,DATE(VALUE(RIGHT(C51,4)),VALUE(LEFT(C51,FIND("/",C51)-1)),VALUE(MID(C51,FIND("/",C51)+1,FIND("/",C51,FIND("/",C51)+1)-FIND("/",C51)-1)))) -> 42112 | E51: =D51 -> 42112 | F51: 4/22/2015 | G51: Standard Class | H51: DP-13000 | I51: Consumer | J51: United States | K51: New Albany | L51: Indiana | M51: Central | N51: OFF-BI-10004410 | O51: Office Supplies | P51: Binders | Q51: C-Line Peel & Stick Add-On Filing Pockets, 8-3/4 x 5-1/8, 10/Pack | R51: 38.22 | S51: 6 | T51: 0 | U51: 17.9634
A52: 51 | B52: CA-2015-115742 | C52: 4/18/2015 | D52: =IF(ISNUMBER(C52),C52,DATE(VALUE(RIGHT(C52,4)),VALUE(LEFT(C52,FIND("/",C52)-1)),VALUE(MID(C52,FIND("/",C52)+1,FIND("/",C52,FIND("/",C52)+1)-FIND("/",C52)-1)))) -> 42112 | E52: =D52 -> 42112 | F52: 4/22/2015 | G52: Standard Class | H52: DP-13000 | I52: Consumer | J52: United States | K52: New Albany | L52: Indiana | M52: Central | N52: OFF-LA-10002762 | O52: Office Supplies | P52: Labels | Q52: Avery 485 | R52: 75.18 | S52: 6 | T52: 0 | U52: 35.3346
A53: 52 | B53: CA-2015-115742 | C53: 4/18/2015 | D53: =IF(ISNUMBER(C53),C53,DATE(VALUE(RIGHT(C53,4)),VALUE(LEFT(C53,FIND("/",C53)-1)),VALUE(MID(C53,FIND("/",C53)+1,FIND("/",C53,FIND("/",C53)+1)-FIND("/",C53)-1)))) -> 42112 | E53: =D53 -> 42112 | F53: 4/22/2015 | G53: Standard Class | H53: DP-13000 | I53: Consumer | J53: United States | K53: New Albany | L53: Indiana | M53: Central | N53: FUR-FU-10001706 | O53: Furniture | P53: Furnishings | Q53: Longer-Life Soft White Bulbs | R53: 6.16 | S53: 2 | T53: 0 | U53: 2.9568
A54: 53 | B54: CA-2015-115742 | C54: 4/18/2015 | D54: =IF(ISNUMBER(C54),C54,DATE(VALUE(RIGHT(C54,4)),VALUE(LEFT(C54,FIND("/",C54)-1)),VALUE(MID(C54,FIND("/",C54)+1,FIND("/",C54,FIND("/",C54)+1)-FIND("/",C54)-1)))) -> 42112 | E54: =D54 -> 42112 | F54: 4/22/2015 | G54: Standard Class | H54: DP-13000 | I54: Consumer | J54: United States | K54: New Albany | L54: Indiana | M54: Central | N54: FUR-CH-10003061 | O54: Furniture | P54: Chairs | Q54: Global Leather Task Chair, Black | R54: 89.99 | S54: 1 | T54: 0 | U54: 17.0981
A55: 54 | B55: CA-2016-105816 | C55: 42686 | D55: =IF(ISNUMBER(C55),C55,DATE(VALUE(RIGHT(C55,4)),VALUE(LEFT(C55,FIND("/",C55)-1)),VALUE(MID(C55,FIND("/",C55)+1,FIND("/",C55,FIND("/",C55)+1)-FIND("/",C55)-1)))) -> 42686 | E55: =D55 -> 42686 | F55: 12/17/2016 | G55: Standard Class | H55: JM-15265 | I55: Corporate | J55: United States | K55: New York City | L55: New York | M55: East | N55: OFF-FA-10000304 | O55: Office Supplies | P55: Fasteners | Q55: Advantus Push Pins | R55: 15.26 | S55: 7 | T55: 0 | U55: 6.2566
A56: 55 | B56: CA-2016-105816 | C56: 42686 | D56: =IF(ISNUMBER(C56),C56,DATE(VALUE(RIGHT(C56,4)),VALUE(LEFT(C56,FIND("/",C56)-1)),VALUE(MID(C56,FIND("/",C56)+1,FIND("/",C56,FIND("/",C56)+1)-FIND("/",C56)-1)))) -> 42686 | E56: =D56 -> 42686 | F56: 12/17/2016 | G56: Standard Class | H56: JM-15265 | I56: Corporate | J56: United States | K56: New York City | L56: New York | M56: East | N56: TEC-PH-10002447 | O56: Technology | P56: Phones | Q56: AT&T CL83451 4-Handset Telephone | R56: 1029.95 | S56: 5 | T56: 0 | U56: 298.6855
A57: 56 | B57: CA-2016-111682 | C57: 6/17/2016 | D57: =IF(ISNUMBER(C57),C57,DATE(VALUE(RIGHT(C57,4)),VALUE(LEFT(C57,FIND("/",C57)-1)),VALUE(MID(C57,FIND("/",C57)+1,FIND("/",C57,FIND("/",C57)+1)-FIND("/",C57)-1)))) -> 42538 | E57: =D57 -> 42538 | F57: 6/18/2016 | G57: First Class | H57: TB-21055 | I57: Consumer | J57: United States | K57: Troy | L57: New York | M57: East | N57: OFF-ST-10000604 | O57: Office Supplies | P57: Storage | Q57: Home/Office Personal File Carts | R57: 208.56 | S57: 6 | T57: 0 | U57: 52.14
A58: 57 | B58: CA-2016-111682 | C58: 6/17/2016 | D58: =IF(ISNUMBER(C58),C58,DATE(VALUE(RIGHT(C58,4)),VALUE(LEFT(C58,FIND("/",C58)-1)),VALUE(MID(C58,FIND("/",C58)+1,FIND("/",C58,FIND("/",C58)+1)-FIND("/",C58)-1)))) -> 42538 | E58: =D58 -> 42538 | F58: 6/18/2016 | G58: First Class | H58: TB-21055 | I58: Consumer | J58: United States | K58: Troy | L58: New York | M58: East | N58: OFF-PA-10001569 | O58: Office Supplies | P58: Paper | Q58: Xerox 232 | R58: 32.4 | S58: 5 | T58: 0 | U58: 15.552
A59: 58 | B59: CA-2016-111682 | C59: 6/17/2016 | D59: =IF(ISNUMBER(C59),C59,DATE(VALUE(RIGHT(C59,4)),VALUE(LEFT(C59,FIND("/",C59)-1)),VALUE(MID(C59,FIND("/",C59)+1,FIND("/",C59,FIND("/",C59)+1)-FIND("/",C59)-1)))) -> 42538 | E59: =D59 -> 42538 | F59: 6/18/2016 | G59: First Class | H59: TB-21055 | I59: Consumer | J59: United States | K59: Troy | L59: New York | M59: East | N59: FUR-CH-10003968 | O59: Furniture | P59: Chairs | Q59: Novimex Turbo Task Chair | R59: 319.41 | S59: 5 | T59: 0.1 | U59: 7.098
A60: 59 | B60: CA-2016-111682 | C60: 6/17/2016 | D60: =IF(ISNUMBER(C60),C60,DATE(VALUE(RIGHT(C60,4)),VALUE(LEFT(C60,FIND("/",C60)-1)),VALUE(MID(C60,FIND("/",C60)+1,FIND("/",C60,FIND("/",C60)+1)-FIND("/",C60)-1)))) -> 42538 | E60: =D60 -> 42538 | F60: 6/18/2016 | G60: First Class | H60: TB-21055 | I60: Consumer | J60: United States | K60: Troy | L60: New York | M60: East | N60: OFF-PA-10000587 | O60: Office Supplies | P60: Paper | Q60: Array Parchment Paper, Assorted Colors | R60: 14.56 | S60: 2 | T60: 0 | U60: 6.9888
A61: 60 | B61: CA-2016-111682 | C61: 6/17/2016 | D61: =IF(ISNUMBER(C61),C61,DATE(VALUE(RIGHT(C61,4)),VALUE(LEFT(C61,FIND("/",C61)-1)),VALUE(MID(C61,FIND("/",C61)+1,FIND("/",C61,FIND("/",C61)+1)-FIND("/",C61)-1)))) -> 42538 | E61: =D61 -> 42538 | F61: 6/18/2016 | G61: First Class | H61: TB-21055 | I61: Consumer | J61: United States | K61: Troy | L61: New York | M61: East | N61: TEC-AC-10002167 | O61: Technology | P61: Accessories | Q61: ImationÂ 8gb Micro Traveldrive Usb 2.0Â Flash Drive | R61: 30 | S61: 2 | T61: 0 | U61: 3.3
A62: 61 | B62: CA-2016-111682 | C62: 6/17/2016 | D62: =IF(ISNUMBER(C62),C62,DATE(VALUE(RIGHT(C62,4)),VALUE(LEFT(C62,FIND("/",C62)-1)),VALUE(MID(C62,FIND("/",C62)+1,FIND("/",C62,FIND("/",C62)+1)-FIND("/",C62)-1)))) -> 42538 | E62: =D62 -> 42538 | F62: 6/18/2016 | G62: First Class | H62: TB-21055 | I62: Consumer | J62: United States | K62: Troy | L62: New York | M62: East | N62: OFF-BI-10001460 | O62: Office Supplies | P62: Binders | Q62: Plastic Binding Combs | R62: 48.48 | S62: 4 | T62: 0.2 | U62: 16.362
A63: 62 | B63: CA-2016-111682 | C63: 6/17/2016 | D63: =IF(ISNUMBER(C63),C63,DATE(VALUE(RIGHT(C63,4)),VALUE(LEFT(C63,FIND("/",C63)-1)),VALUE(MID(C63,FIND("/",C63)+1,FIND("/",C63,FIND("/",C63)+1)-FIND("/",C63)-1)))) -> 42538 | E63: =D63 -> 42538 | F63: 6/18/2016 | G63: First Class | H63: TB-21055 | I63: Consumer | J63: United States | K63: Troy | L63: New York | M63: East | N63: OFF-AR-10001868 | O63: Office Supplies | P63: Art | Q63: Prang Dustless Chalk Sticks | R63: 1.68 | S63: 1 | T63: 0 | U63: 0.84
A64: 63 | B64: CA-2015-135545 | C64: 11/24/2015 | D64: =IF(ISNUMBER(C64),C64,DATE(VALUE(RIGHT(C64,4)),VALUE(LEFT(C64,FIND("/",C64)-1)),VALUE(MID(C64,FIND("/",C64)+1,FIND("/",C64,FIND("/",C64)+1)-FIND("/",C64)-1)))) -> 42332 | E64: =D64 -> 42332 | F64: 11/30/2015 | G64: Standard Class | H64: KM-16720 | I64: Consumer | J64: United States | K64: Los Angeles | L64: California | M64: West | N64: TEC-AC-10004633 | O64: Technology | P64: Accessories | Q64: Verbatim 25 GB 6x Blu-ray Single Layer Recordable Disc, 3/Pack | R64: 13.98 | S64: 2 | T64: 0 | U64: 6.1512
A65: 64 | B65: CA-2015-135545 | C65: 11/24/2015 | D65: =IF(ISNUMBER(C65),C65,DATE(VALUE(RIGHT(C65,4)),VALUE(LEFT(C65,FIND("/",C65)-1)),VALUE(MID(C65,FIND("/",C65)+1,FIND("/",C65,FIND("/",C65)+1)-FIND("/",C65)-1)))) -> 42332 | E65: =D65 -> 42332 | F65: 11/30/2015 | G65: Standard Class | H65: KM-16720 | I65: Consumer | J65: United States | K65: Los Angeles | L65: California | M65: West | N65: OFF-BI-10001078 | O65: Office Supplies | P65: Binders | Q65: Acco PRESSTEX Data Binder with Storage Hooks, Dark Blue, 14 7/8" X 11" | R65: 25.824 | S65: 6 | T65: 0.2 | U65: 9.3612
A66: 65 | B66: CA-2015-135545 | C66: 11/24/2015 | D66: =IF(ISNUMBER(C66),C66,DATE(VALUE(RIGHT(C66,4)),VALUE(LEFT(C66,FIND("/",C66)-1)),VALUE(MID(C66,FIND("/",C66)+1,FIND("/",C66,FIND("/",C66)+1)-FIND("/",C66)-1)))) -> 42332 | E66: =D66 -> 42332 | F66: 11/30/2015 | G66: Standard Class | H66: KM-16720 | I66: Consumer | J66: United States | K66: Los Angeles | L66: California | M66: West | N66: OFF-PA-10003892 | O66: Office Supplies | P66: Paper | Q66: Xerox 1943 | R66: 146.73 | S66: 3 | T66: 0 | U66: 68.9631
A67: 66 | B67: CA-2015-135545 | C67: 11/24/2015 | D67: =IF(ISNUMBER(C67),C67,DATE(VALUE(RIGHT(C67,4)),VALUE(LEFT(C67,FIND("/",C67)-1)),VALUE(MID(C67,FIND("/",C67)+1,FIND("/",C67,FIND("/",C67)+1)-FIND("/",C67)-1)))) -> 42332 | E67: =D67 -> 42332 | F67: 11/30/2015 | G67: Standard Class | H67: KM-16720 | I67: Consumer | J67: United States | K67: Los Angeles | L67: California | M67: West | N67: FUR-FU-10000397 | O67: Furniture | P67: Furnishings | Q67: Luxo Economy Swing Arm Lamp | R67: 79.76 | S67: 4 | T67: 0 | U67: 22.3328
A68: 67 | B68: US-2015-164175 | C68: 4/30/2015 | D68: =IF(ISNUMBER(C68),C68,DATE(VALUE(RIGHT(C68,4)),VALUE(LEFT(C68,FIND("/",C68)-1)),VALUE(MID(C68,FIND("/",C68)+1,FIND("/",C68,FIND("/",C68)+1)-FIND("/",C68)-1)))) -> 42124 | E68: =D68 -> 42124 | F68: 42129 | G68: Standard Class | H68: PS-18970 | I68: Home Office | J68: United States | K68: Chicago | L68: Illinois | M68: Central | N68: FUR-CH-10001146 | O68: Furniture | P68: Chairs | Q68: Global Value Mid-Back Manager's Chair, Gray | R68: 213.115 | S68: 5 | T68: 0.3 | U68: -15.2225
A69: 68 | B69: CA-2014-106376 | C69: 41771 | D69: =IF(ISNUMBER(C69),C69,DATE(VALUE(RIGHT(C69,4)),VALUE(LEFT(C69,FIND("/",C69)-1)),VALUE(MID(C69,FIND("/",C69)+1,FIND("/",C69,FIND("/",C69)+1)-FIND("/",C69)-1)))) -> 41771 | E69: =D69 -> 41771 | F69: 41924 | G69: Standard Class | H69: BS-11590 | I69: Corporate | J69: United States | K69: Gilbert | L69: Arizona | M69: West | N69: OFF-AR-10002671 | O69: Office Supplies | P69: Art | Q69: Hunt BOSTON Model 1606 High-Volume Electric Pencil Sharpener, Beige | R69: 1113.024 | S69: 8 | T69: 0.2 | U69: 111.3024
A70: 69 | B70: CA-2014-106376 | C70: 41771 | D70: =IF(ISNUMBER(C70),C70,DATE(VALUE(RIGHT(C70,4)),VALUE(LEFT(C70,FIND("/",C70)-1)),VALUE(MID(C70,FIND("/",C70)+1,FIND("/",C70,FIND("/",C70)+1)-FIND("/",C70)-1)))) -> 41771 | E70: =D70 -> 41771 | F70: 41924 | G70: Standard Class | H70: BS-11590 | I70: Corporate | J70: United States | K70: Gilbert | L70: Arizona | M70: West | N70: TEC-PH-10002726 | O70: Technology | P70: Phones | Q70: netTALK DUO VoIP Telephone Service | R70: 167.968 | S70: 4 | T70: 0.2 | U70: 62.988
A71: 70 | B71: CA-2016-119823 | C71: 42466 | D71: =IF(ISNUMBER(C71),C71,DATE(VALUE(RIGHT(C71,4)),VALUE(LEFT(C71,FIND("/",C71)-1)),VALUE(MID(C71,FIND("/",C71)+1,FIND("/",C71,FIND("/",C71)+1)-FIND("/",C71)-1)))) -> 42466 | E71: =D71 -> 42466 | F71: 42527 | G71: First Class | H71: KD-16270 | I71: Consumer | J71: United States | K71: Springfield | L71: Virginia | M71: South | N71: OFF-PA-10000482 | O71: Office Supplies | P71: Paper | Q71: Snap-A-Way Black Print Carbonless Ruled Speed Letter, Triplicate | R71: 75.88 | S71: 2 | T71: 0 | U71: 35.6636
A72: 71 | B72: CA-2016-106075 | C72: 9/18/2016 | D72: =IF(ISNUMBER(C72),C72,DATE(VALUE(RIGHT(C72,4)),VALUE(LEFT(C72,FIND("/",C72)-1)),VALUE(MID(C72,FIND("/",C72)+1,FIND("/",C72,FIND("/",C72)+1)-FIND("/",C72)-1)))) -> 42631 | E72: =D72 -> 42631 | F72: 9/23/2016 | G72: Standard Class | H72: HM-14980 | I72: Consumer | J72: United States | K72: New York City | L72: New York | M72: East | N72: OFF-BI-10004654 | O72: Office Supplies | P72: Binders | Q72: Avery Binding System Hidden Tab Executive Style Index Sets | R72: 4.616 | S72: 1 | T72: 0.2 | U72: 1.731
A73: 72 | B73: CA-2017-114440 | C73: 9/14/2017 | D73: =IF(ISNUMBER(C73),C73,DATE(VALUE(RIGHT(C73,4)),VALUE(LEFT(C73,FIND("/",C73)-1)),VALUE(MID(C73,FIND("/",C73)+1,FIND("/",C73,FIND("/",C73)+1)-FIND("/",C73)-1)))) -> 42992 | E73: =D73 -> 42992 | F73: 9/17/2017 | G73: Second Class | H73: TB-21520 | I73: Consumer | J73: United States | K73: Jackson | L73: Michigan | M73: Central | N73: OFF-PA-10004675 | O73: Office Supplies | P73: Paper | Q73: Telephone Message Books with Fax/Mobile Section, 5 1/2" x 3 3/16" | R73: 19.05 | S73: 3 | T73: 0 | U73: 8.763
A74: 73 | B74: US-2015-134026 | C74: 4/26/2015 | D74: =IF(ISNUMBER(C74),C74,DATE(VALUE(RIGHT(C74,4)),VALUE(LEFT(C74,FIND("/",C74)-1)),VALUE(MID(C74,FIND("/",C74)+1,FIND("/",C74,FIND("/",C74)+1)-FIND("/",C74)-1)))) -> 42120 | E74: =D74 -> 42120 | F74: 42040 | G74: Standard Class | H74: JE-15745 | I74: Consumer | J74: United States | K74: Memphis | L74: Tennessee | M74: South | N74: FUR-CH-10000513 | O74: Furniture | P74: Chairs | Q74: High-Back Leather Manager's Chair | R74: 831.936 | S74: 8 | T74: 0.2 | U74: -114.3912
A75: 74 | B75: US-2015-134026 | C75: 4/26/2015 | D75: =IF(ISNUMBER(C75),C75,DATE(VALUE(RIGHT(C75,4)),VALUE(LEFT(C75,FIND("/",C75)-1)),VALUE(MID(C75,FIND("/",C75)+1,FIND("/",C75,FIND("/",C75)+1)-FIND("/",C75)-1)))) -> 42120 | E75: =D75 -> 42120 | F75: 42040 | G75: Standard Class | H75: JE-15745 | I75: Consumer | J75: United States | K75: Memphis | L75: Tennessee | M75: South | N75: FUR-FU-10003708 | O75: Furniture | P75: Furnishings | Q75: Tenex Traditional Chairmats for Medium Pile Carpet, Standard Lip, 36" x 48" | R75: 97.04 | S75: 2 | T75: 0.2 | U75: 1.213
A76: 75 | B76: US-2015-134026 | C76: 4/26/2015 | D76: =IF(ISNUMBER(C76),C76,DATE(VALUE(RIGHT(C76,4)),VALUE(LEFT(C76,FIND("/",C76)-1)),VALUE(MID(C76,FIND("/",C76)+1,FIND("/",C76,FIND("/",C76)+1)-FIND("/",C76)-1)))) -> 42120 | E76: =D76 -> 42120 | F76: 42040 | G76: Standard Class | H76: JE-15745 | I76: Consumer | J76: United States | K76: Memphis | L76: Tennessee | M76: South | N76: OFF-ST-10004123 | O76: Office Supplies | P76: Storage | Q76: Safco Industrial Wire Shelving System | R76: 72.784 | S76: 1 | T76: 0.2 | U76: -18.196
A77: 76 | B77: US-2017-118038 | C77: 42990 | D77: =IF(ISNUMBER(C77),C77,DATE(VALUE(RIGHT(C77,4)),VALUE(LEFT(C77,FIND("/",C77)-1)),VALUE(MID(C77,FIND("/",C77)+1,FIND("/",C77,FIND("/",C77)+1)-FIND("/",C77)-1)))) -> 42990 | E77: =D77 -> 42990 | F77: 43051 | G77: First Class | H77: KB-16600 | I77: Corporate | J77: United States | K77: Houston | L77: Texas | M77: Central | N77: OFF-BI-10004182 | O77: Office Supplies | P77: Binders | Q77: Economy Binders | R77: 1.248 | S77: 3 | T77: 0.8 | U77: -1.9344
A78: 77 | B78: US-2017-118038 | C78: 42990 | D78: =IF(ISNUMBER(C78),C78,DATE(VALUE(RIGHT(C78,4)),VALUE(LEFT(C78,FIND("/",C78)-1)),VALUE(MID(C78,FIND("/",C78)+1,FIND("/",C78,FIND("/",C78)+1)-FIND("/",C78)-1)))) -> 42990 | E78: =D78 -> 42990 | F78: 43051 | G78: First Class | H78: KB-16600 | I78: Corporate | J78: United States | K78: Houston | L78: Texas | M78: Central | N78: FUR-FU-10000260 | O78: Furniture | P78: Furnishings | Q78: 6" Cubicle Wall Clock, Black | R78: 9.708 | S78: 3 | T78: 0.6 | U78: -5.8248
A79: 78 | B79: US-2017-118038 | C79: 42990 | D79: =IF(ISNUMBER(C79),C79,DATE(VALUE(RIGHT(C79,4)),VALUE(LEFT(C79,FIND("/",C79)-1)),VALUE(MID(C79,FIND("/",C79)+1,FIND("/",C79,FIND("/",C79)+1)-FIND("/",C79)-1)))) -> 42990 | E79: =D79 -> 42990 | F79: 43051 | G79: First Class | H79: KB-16600 | I79: Corporate | J79: United States | K79: Houston | L79: Texas | M79: Central | N79: OFF-ST-10000615 | O79: Office Supplies | P79: Storage | Q79: SimpliFile Personal File, Black Granite, 15w x 6-15/16d x 11-1/4h | R79: 27.24 | S79: 3 | T79: 0.2 | U79: 2.724
A80: 79 | B80: US-2014-147606 | C80: 11/26/2014 | D80: =IF(ISNUMBER(C80),C80,DATE(VALUE(RIGHT(C80,4)),VALUE(LEFT(C80,FIND("/",C80)-1)),VALUE(MID(C80,FIND("/",C80)+1,FIND("/",C80,FIND("/",C80)+1)-FIND("/",C80)-1)))) -> 41969 | E80: =D80 -> 41969 | F80: 41651 | G80: Second Class | H80: JE-15745 | I80: Consumer | J80: United States | K80: Houston | L80: Texas | M80: Central | N80: FUR-FU-10003194 | O80: Furniture | P80: Furnishings | Q80: Eldon Expressions Desk Accessory, Wood Pencil Holder, Oak | R80: 19.3 | S80: 5 | T80: 0.6 | U80: -14.475
A81: 80 | B81: CA-2016-127208 | C81: 42710 | D81: =IF(ISNUMBER(C81),C81,DATE(VALUE(RIGHT(C81,4)),VALUE(LEFT(C81,FIND("/",C81)-1)),VALUE(MID(C81,FIND("/",C81)+1,FIND("/",C81,FIND("/",C81)+1)-FIND("/",C81)-1)))) -> 42710 | E81: =D81 -> 42710 | F81: 6/15/2016 | G81: First Class | H81: SC-20770 | I81: Corporate | J81: United States | K81: Decatur | L81: Alabama | M81: South | N81: OFF-AP-10002118 | O81: Office Supplies | P81: Appliances | Q81: 1.7 Cubic Foot Compact "Cube" Office Refrigerators | R81: 208.16 | S81: 1 | T81: 0 | U81: 56.2032
A82: 81 | B82: CA-2016-127208 | C82: 42710 | D82: =IF(ISNUMBER(C82),C82,DATE(VALUE(RIGHT(C82,4)),VALUE(LEFT(C82,FIND("/",C82)-1)),VALUE(MID(C82,FIND("/",C82)+1,FIND("/",C82,FIND("/",C82)+1)-FIND("/",C82)-1)))) -> 42710 | E82: =D82 -> 42710 | F82: 6/15/2016 | G82: First Class | H82: SC-20770 | I82: Corporate | J82: United States | K82: Decatur | L82: Alabama | M82: South | N82: OFF-BI-10002309 | O82: Office Supplies | P82: Binders | Q82: Avery Heavy-Duty EZD Binder With Locking Rings | R82: 16.74 | S82: 3 | T82: 0 | U82: 8.0352
A83: 82 | B83: CA-2014-139451 | C83: 41983 | D83: =IF(ISNUMBER(C83),C83,DATE(VALUE(RIGHT(C83,4)),VALUE(LEFT(C83,FIND("/",C83)-1)),VALUE(MID(C83,FIND("/",C83)+1,FIND("/",C83,FIND("/",C83)+1)-FIND("/",C83)-1)))) -> 41983 | E83: =D83 -> 41983 | F83: 10/16/2014 | G83: Standard Class | H83: DN-13690 | I83: Consumer | J83: United States | K83: San Francisco | L83: California | M83: West | N83: OFF-AR-10002053 | O83: Office Supplies | P83: Art | Q83: Premium Writing Pencils, Soft, #2 by Central Association for the Blind | R83: 14.9 | S83: 5 | T83: 0 | U83: 4.172
A84: 83 | B84: CA-2014-139451 | C84: 41983 | D84: =IF(ISNUMBER(C84),C84,DATE(VALUE(RIGHT(C84,4)),VALUE(LEFT(C84,FIND("/",C84)-1)),VALUE(MID(C84,FIND("/",C84)+1,FIND("/",C84,FIND("/",C84)+1)-FIND("/",C84)-1)))) -> 41983 | E84: =D84 -> 41983 | F84: 10/16/2014 | G84: Standard Class | H84: DN-13690 | I84: Consumer | J84: United States | K84: San Francisco | L84: California | M84: West | N84: OFF-ST-10002370 | O84: Office Supplies | P84: Storage | Q84: Sortfiler Multipurpose Personal File Organizer, Black | R84: 21.39 | S84: 1 | T84: 0 | U84: 6.2031
A85: 84 | B85: CA-2015-149734 | C85: 42072 | D85: =IF(ISNUMBER(C85),C85,DATE(VALUE(RIGHT(C85,4)),VALUE(LEFT(C85,FIND("/",C85)-1)),VALUE(MID(C85,FIND("/",C85)+1,FIND("/",C85,FIND("/",C85)+1)-FIND("/",C85)-1)))) -> 42072 | E85: =D85 -> 42072 | F85: 42225 | G85: Standard Class | H85: JC-16105 | I85: Corporate | J85: United States | K85: Durham | L85: North Carolina | M85: South | N85: OFF-EN-10000927 | O85: Office Supplies | P85: Envelopes | Q85: Jet-Pak Recycled Peel 'N' Seal Padded Mailers | R85: 200.984 | S85: 7 | T85: 0.2 | U85: 62.8075
A86: 85 | B86: US-2017-119662 | C86: 11/13/2017 | D86: =IF(ISNUMBER(C86),C86,DATE(VALUE(RIGHT(C86,4)),VALUE(LEFT(C86,FIND("/",C86)-1)),VALUE(MID(C86,FIND("/",C86)+1,FIND("/",C86,FIND("/",C86)+1)-FIND("/",C86)-1)))) -> 43052 | E86: =D86 -> 43052 | F86: 11/16/2017 | G86: First Class | H86: CS-12400 | I86: Home Office | J86: United States | K86: Chicago | L86: Illinois | M86: Central | N86: OFF-ST-10003656 | O86: Office Supplies | P86: Storage | Q86: Safco Industrial Wire Shelving | R86: 230.376 | S86: 3 | T86: 0.2 | U86: -48.9549
A87: 86 | B87: CA-2017-140088 | C87: 5/28/2017 | D87: =IF(ISNUMBER(C87),C87,DATE(VALUE(RIGHT(C87,4)),VALUE(LEFT(C87,FIND("/",C87)-1)),VALUE(MID(C87,FIND("/",C87)+1,FIND("/",C87,FIND("/",C87)+1)-FIND("/",C87)-1)))) -> 42883 | E87: =D87 -> 42883 | F87: 5/30/2017 | G87: Second Class | H87: PO-18865 | I87: Consumer | J87: United States | K87: Columbia | L87: South Carolina | M87: South | N87: FUR-CH-10000863 | O87: Furniture | P87: Chairs | Q87: Novimex Swivel Fabric Task Chair | R87: 301.96 | S87: 2 | T87: 0 | U87: 33.2156
A88: 87 | B88: CA-2017-155558 | C88: 10/26/2017 | D88: =IF(ISNUMBER(C88),C88,DATE(VALUE(RIGHT(C88,4)),VALUE(LEFT(C88,FIND("/",C88)-1)),VALUE(MID(C88,FIND("/",C88)+1,FIND("/",C88,FIND("/",C88)+1)-FIND("/",C88)-1)))) -> 43034 | E88: =D88 -> 43034 | F88: 42777 | G88: Standard Class | H88: PG-18895 | I88: Consumer | J88: United States | K88: Rochester | L88: Minnesota | M88: Central | N88: TEC-AC-10001998 | O88: Technology | P88: Accessories | Q88: LogitechÂ LS21 Speaker System - PC Multimedia - 2.1-CH - Wired | R88: 19.99 | S88: 1 | T88: 0 | U88: 6.7966
A89: 88 | B89: CA-2017-155558 | C89: 10/26/2017 | D89: =IF(ISNUMBER(C89),C89,DATE(VALUE(RIGHT(C89,4)),VALUE(LEFT(C89,FIND("/",C89)-1)),VALUE(MID(C89,FIND("/",C89)+1,FIND("/",C89,FIND("/",C89)+1)-FIND("/",C89)-1)))) -> 43034 | E89: =D89 -> 43034 | F89: 42777 | G89: Standard Class | H89: PG-18895 | I89: Consumer | J89: United States | K89: Rochester | L89: Minnesota | M89: Central | N89: OFF-LA-10000134 | O89: Office Supplies | P89: Labels | Q89: Avery 511 | R89: 6.16 | S89: 2 | T89: 0 | U89: 2.9568
A90: 89 | B90: CA-2016-159695 | C90: 42494 | D90: =IF(ISNUMBER(C90),C90,DATE(VALUE(RIGHT(C90,4)),VALUE(LEFT(C90,FIND("/",C90)-1)),VALUE(MID(C90,FIND("/",C90)+1,FIND("/",C90,FIND("/",C90)+1)-FIND("/",C90)-1)))) -> 42494 | E90: =D90 -> 42494 | F90: 42647 | G90: Second Class | H90: GM-14455 | I90: Home Office | J90: United States | K90: Houston | L90: Texas | M90: Central | N90: OFF-ST-10003442 | O90: Office Supplies | P90: Storage | Q90: Eldon Portable Mobile Manager | R90: 158.368 | S90: 7 | T90: 0.2 | U90: 13.8572
A91: 90 | B91: CA-2016-109806 | C91: 9/17/2016 | D91: =IF(ISNUMBER(C91),C91,DATE(VALUE(RIGHT(C91,4)),VALUE(LEFT(C91,FIND("/",C91)-1)),VALUE(MID(C91,FIND("/",C91)+1,FIND("/",C91,FIND("/",C91)+1)-FIND("/",C91)-1)))) -> 42630 | E91: =D91 -> 42630 | F91: 9/22/2016 | G91: Standard Class | H91: JS-15685 | I91: Corporate | J91: United States | K91: Los Angeles | L91: California | M91: West | N91: OFF-AR-10004930 | O91: Office Supplies | P91: Art | Q91: Turquoise Lead Holder with Pocket Clip | R91: 20.1 | S91: 3 | T91: 0 | U91: 6.633
A92: 91 | B92: CA-2016-109806 | C92: 9/17/2016 | D92: =IF(ISNUMBER(C92),C92,DATE(VALUE(RIGHT(C92,4)),VALUE(LEFT(C92,FIND("/",C92)-1)),VALUE(MID(C92,FIND("/",C92)+1,FIND("/",C92,FIND("/",C92)+1)-FIND("/",C92)-1)))) -> 42630 | E92: =D92 -> 42630 | F92: 9/22/2016 | G92: Standard Class | H92: JS-15685 | I92: Corporate | J92: United States | K92: Los Angeles | L92: California | M92: West | N92: TEC-PH-10004093 | O92: Technology | P92: Phones | Q92: Panasonic Kx-TS550 | R92: 73.584 | S92: 2 | T92: 0.2 | U92: 8.2782
A93: 92 | B93: CA-2016-109806 | C93: 9/17/2016 | D93: =IF(ISNUMBER(C93),C93,DATE(VALUE(RIGHT(C93,4)),VALUE(LEFT(C93,FIND("/",C93)-1)),VALUE(MID(C93,FIND("/",C93)+1,FIND("/",C93,FIND("/",C93)+1)-FIND("/",C93)-1)))) -> 42630 | E93: =D93 -> 42630 | F93: 9/22/2016 | G93: Standard Class | H93: JS-15685 | I93: Corporate | J93: United States | K93: Los Angeles | L93: California | M93: West | N93: OFF-PA-10000304 | O93: Office Supplies | P93: Paper | Q93: Xerox 1995 | R93: 6.48 | S93: 1 | T93: 0 | U93: 3.1104
A94: 93 | B94: CA-2015-149587 | C94: 1/31/2015 | D94: =IF(ISNUMBER(C94),C94,DATE(VALUE(RIGHT(C94,4)),VALUE(LEFT(C94,FIND("/",C94)-1)),VALUE(MID(C94,FIND("/",C94)+1,FIND("/",C94,FIND("/",C94)+1)-FIND("/",C94)-1)))) -> 42035 | E94: =D94 -> 42035 | F94: 42126 | G94: Second Class | H94: KB-16315 | I94: Consumer | J94: United States | K94: Minneapolis | L94: Minnesota | M94: Central | N94: OFF-PA-10003177 | O94: Office Supplies | P94: Paper | Q94: Xerox 1999 | R94: 12.96 | S94: 2 | T94: 0 | U94: 6.2208
A95: 94 | B95: CA-2015-149587 | C95: 1/31/2015 | D95: =IF(ISNUMBER(C95),C95,DATE(VALUE(RIGHT(C95,4)),VALUE(LEFT(C95,FIND("/",C95)-1)),VALUE(MID(C95,FIND("/",C95)+1,FIND("/",C95,FIND("/",C95)+1)-FIND("/",C95)-1)))) -> 42035 | E95: =D95 -> 42035 | F95: 42126 | G95: Second Class | H95: KB-16315 | I95: Consumer | J95: United States | K95: Minneapolis | L95: Minnesota | M95: Central | N95: FUR-FU-10003799 | O95: Furniture | P95: Furnishings | Q95: Seth Thomas 13 1/2" Wall Clock | R95: 53.34 | S95: 3 | T95: 0 | U95: 16.5354
A96: 95 | B96: CA-2015-149587 | C96: 1/31/2015 | D96: =IF(ISNUMBER(C96),C96,DATE(VALUE(RIGHT(C96,4)),VALUE(LEFT(C96,FIND("/",C96)-1)),VALUE(MID(C96,FIND("/",C96)+1,FIND("/",C96,FIND("/",C96)+1)-FIND("/",C96)-1)))) -> 42035 | E96: =D96 -> 42035 | F96: 42126 | G96: Second Class | H96: KB-16315 | I96: Consumer | J96: United States | K96: Minneapolis | L96: Minnesota | M96: Central | N96: OFF-BI-10002852 | O96: Office Supplies | P96: Binders | Q96: Ibico Standard Transparent Covers | R96: 32.96 | S96: 2 | T96: 0 | U96: 16.1504
A97: 96 | B97: US-2017-109484 | C97: 42897 | D97: =IF(ISNUMBER(C97),C97,DATE(VALUE(RIGHT(C97,4)),VALUE(LEFT(C97,FIND("/",C97)-1)),VALUE(MID(C97,FIND("/",C97)+1,FIND("/",C97,FIND("/",C97)+1)-FIND("/",C97)-1)))) -> 42897 | E97: =D97 -> 42897 | F97: 43080 | G97: Standard Class | H97: RB-19705 | I97: Home Office | J97: United States | K97: Portland | L97: Oregon | M97: West | N97: OFF-BI-10004738 | O97: Office Supplies | P97: Binders | Q97: Flexible Leather- Look Classic Collection Ring Binder | R97: 5.682 | S97: 1 | T97: 0.7 | U97: -3.788
A98: 97 | B98: CA-2017-161018 | C98: 42989 | D98: =IF(ISNUMBER(C98),C98,DATE(VALUE(RIGHT(C98,4)),VALUE(LEFT(C98,FIND("/",C98)-1)),VALUE(MID(C98,FIND("/",C98)+1,FIND("/",C98,FIND("/",C98)+1)-FIND("/",C98)-1)))) -> 42989 | E98: =D98 -> 42989 | F98: 43050 | G98: Second Class | H98: PN-18775 | I98: Home Office | J98: United States | K98: New York City | L98: New York | M98: East | N98: FUR-FU-10000629 | O98: Furniture | P98: Furnishings | Q98: 9-3/4 Diameter Round Wall Clock | R98: 96.53 | S98: 7 | T98: 0 | U98: 40.5426
A99: 98 | B99: CA-2017-157833 | C99: 6/17/2017 | D99: =IF(ISNUMBER(C99),C99,DATE(VALUE(RIGHT(C99,4)),VALUE(LEFT(C99,FIND("/",C99)-1)),VALUE(MID(C99,FIND("/",C99)+1,FIND("/",C99,FIND("/",C99)+1)-FIND("/",C99)-1)))) -> 42903 | E99: =D99 -> 42903 | F99: 6/20/2017 | G99: First Class | H99: KD-16345 | I99: Consumer | J99: United States | K99: San Francisco | L99: California | M99: West | N99: OFF-BI-10001721 | O99: Office Supplies | P99: Binders | Q99: Trimflex Flexible Post Binders | R99: 51.312 | S99: 3 | T99: 0.2 | U99: 17.9592
A100: 99 | B100: CA-2016-149223 | C100: 42530 | D100: =IF(ISNUMBER(C100),C100,DATE(VALUE(RIGHT(C100,4)),VALUE(LEFT(C100,FIND("/",C100)-1)),VALUE(MID(C100,FIND("/",C100)+1,FIND("/",C100,FIND("/",C100)+1)-FIND("/",C100)-1)))) -> 42530 | E100: =D100 -> 42530 | F100: 42683 | G100: Standard Class | H100: ER-13855 | I100: Corporate | J100: United States | K100: Saint Paul | L100: Minnesota | M100: Central | N100: OFF-AP-10000358 | O100: Office Supplies | P100: Appliances | Q100: Fellowes Basic Home/Office Series Surge Protectors | R100: 77.88 | S100: 6 | T100: 0 | U100: 22.5852
...

Sheet Summary
A1: Month | B1: Total Sales
A2: 41640 | B2: =SUMIFS('Raw Data'!R:R,'Raw Data'!E:E,">="&A2,'Raw Data'!E:E,"<"&EDATE(A2,1)) -> 28953.706
A3: 41671 | B3: =SUMIFS('Raw Data'!R:R,'Raw Data'!E:E,">="&A3,'Raw Data'!E:E,"<"&EDATE(A3,1)) -> 12743.108
A4: 41699 | B4: =SUMIFS('Raw Data'!R:R,'Raw Data'!E:E,">="&A4,'Raw Data'!E:E,"<"&EDATE(A4,1)) -> 54801.906
A5: 41730 | B5: =SUMIFS('Raw Data'!R:R,'Raw Data'!E:E,">="&A5,'Raw Data'!E:E,"<"&EDATE(A5,1)) -> 24710.016
A6: 41760 | B6: =SUMIFS('Raw Data'!R:R,'Raw Data'!E:E,">="&A6,'Raw Data'!E:E,"<"&EDATE(A6,1)) -> 29639.834
A7: 41791 | B7: =SUMIFS('Raw Data'!R:R,'Raw Data'!E:E,">="&A7,'Raw Data'!E:E,"<"&EDATE(A7,1)) -> 29287.031
A8: 41821 | B8: =SUMIFS('Raw Data'!R:R,'Raw Data'!E:E,">="&A8,'Raw Data'!E:E,"<"&EDATE(A8,1)) -> 35341.246 | Y8: Metric | Z8: Result
A9: 41852 | B9: =SUMIFS('Raw Data'!R:R,'Raw Data'!E:E,">="&A9,'Raw Data'!E:E,"<"&EDATE(A9,1)) -> 37854.547 | Y9: Highest Sales Month | Z9: 43040
A10: 41883 | B10: =SUMIFS('Raw Data'!R:R,'Raw Data'!E:E,">="&A10,'Raw Data'!E:E,"<"&EDATE(A10,1)) -> 66110.224 | Y10: Highest Monthly Sales | Z10: 89306.24
A11: 41913 | B11: =SUMIFS('Raw Data'!R:R,'Raw Data'!E:E,">="&A11,'Raw Data'!E:E,"<"&EDATE(A11,1)) -> 34561.947 | Y11: Lowest Sales Month | Z11: 42036
A12: 41944 | B12: =SUMIFS('Raw Data'!R:R,'Raw Data'!E:E,">="&A12,'Raw Data'!E:E,"<"&EDATE(A12,1)) -> 64817.619 | Y12: Lowest Monthly Sales | Z12: 20728.35
A13: 41974 | B13: =SUMIFS('Raw Data'!R:R,'Raw Data'!E:E,">="&A13,'Raw Data'!E:E,"<"&EDATE(A13,1)) -> 65426.315
A14: 42005 | B14: =SUMIFS('Raw Data'!R:R,'Raw Data'!E:E,">="&A14,'Raw Data'!E:E,"<"&EDATE(A14,1)) -> 29347.386
A15: 42036 | B15: =SUMIFS('Raw Data'!R:R,'Raw Data'!E:E,">="&A15,'Raw Data'!E:E,"<"&EDATE(A15,1)) -> 20728.352
A16: 42064 | B16: =SUMIFS('Raw Data'!R:R,'Raw Data'!E:E,">="&A16,'Raw Data'!E:E,"<"&EDATE(A16,1)) -> 40876.611
A17: 42095 | B17: =SUMIFS('Raw Data'!R:R,'Raw Data'!E:E,">="&A17,'Raw Data'!E:E,"<"&EDATE(A17,1)) -> 38056.969
A18: 42125 | B18: =SUMIFS('Raw Data'!R:R,'Raw Data'!E:E,">="&A18,'Raw Data'!E:E,"<"&EDATE(A18,1)) -> 30933.715 | Y18: Year | Z18: Total Sales
A19: 42156 | B19: =SUMIFS('Raw Data'!R:R,'Raw Data'!E:E,">="&A19,'Raw Data'!E:E,"<"&EDATE(A19,1)) -> 28862.198 | Y19: 2014 | Z19: =SUMIFS($B$2:$B$49,$A$2:$A$49,">="&DATE(Y19,1,1),$A$2:$A$49,"<"&DATE(Y19+1,1,1)) -> 484247.5
A20: 42186 | B20: =SUMIFS('Raw Data'!R:R,'Raw Data'!E:E,">="&A20,'Raw Data'!E:E,"<"&EDATE(A20,1)) -> 28730.376 | Y20: 2015 | Z20: =SUMIFS($B$2:$B$49,$A$2:$A$49,">="&DATE(Y20,1,1),$A$2:$A$49,"<"&DATE(Y20+1,1,1)) -> 470532.51
A21: 42217 | B21: =SUMIFS('Raw Data'!R:R,'Raw Data'!E:E,">="&A21,'Raw Data'!E:E,"<"&EDATE(A21,1)) -> 50094.528 | Y21: 2016 | Z21: =SUMIFS($B$2:$B$49,$A$2:$A$49,">="&DATE(Y21,1,1),$A$2:$A$49,"<"&DATE(Y21+1,1,1)) -> 609205.6
A22: 42248 | B22: =SUMIFS('Raw Data'!R:R,'Raw Data'!E:E,">="&A22,'Raw Data'!E:E,"<"&EDATE(A22,1)) -> 66729.329 | Y22: 2017 | Z22: =SUMIFS($B$2:$B$49,$A$2:$A$49,">="&DATE(Y22,1,1),$A$2:$A$49,"<"&DATE(Y22+1,1,1)) -> 733215.26
A23: 42278 | B23: =SUMIFS('Raw Data'!R:R,'Raw Data'!E:E,">="&A23,'Raw Data'!E:E,"<"&EDATE(A23,1)) -> 32025.075
A24: 42309 | B24: =SUMIFS('Raw Data'!R:R,'Raw Data'!E:E,">="&A24,'Raw Data'!E:E,"<"&EDATE(A24,1)) -> 50732.309
A25: 42339 | B25: =SUMIFS('Raw Data'!R:R,'Raw Data'!E:E,">="&A25,'Raw Data'!E:E,"<"&EDATE(A25,1)) -> 53415.661
A26: 42370 | B26: =SUMIFS('Raw Data'!R:R,'Raw Data'!E:E,">="&A26,'Raw Data'!E:E,"<"&EDATE(A26,1)) -> 38048.184
A27: 42401 | B27: =SUMIFS('Raw Data'!R:R,'Raw Data'!E:E,">="&A27,'Raw Data'!E:E,"<"&EDATE(A27,1)) -> 49238.41
A28: 42430 | B28: =SUMIFS('Raw Data'!R:R,'Raw Data'!E:E,">="&A28,'Raw Data'!E:E,"<"&EDATE(A28,1)) -> 49612.045
A29: 42461 | B29: =SUMIFS('Raw Data'!R:R,'Raw Data'!E:E,">="&A29,'Raw Data'!E:E,"<"&EDATE(A29,1)) -> 45192.278
A30: 42491 | B30: =SUMIFS('Raw Data'!R:R,'Raw Data'!E:E,">="&A30,'Raw Data'!E:E,"<"&EDATE(A30,1)) -> 64964.322 | X30: Overall sales trend: Sales show fluctuations month-to-month, but the later years generally contain higher monthly sales values.
A31: 42522 | B31: =SUMIFS('Raw Data'!R:R,'Raw Data'!E:E,">="&A31,'Raw Data'!E:E,"<"&EDATE(A31,1)) -> 38991.943 | X31: Highest sales month: November 2017 recorded the highest monthly sales of ₹89,306.24.
A32: 42552 | B32: =SUMIFS('Raw Data'!R:R,'Raw Data'!E:E,">="&A32,'Raw Data'!E:E,"<"&EDATE(A32,1)) -> 42773.395 | X32: Lowest sales month: February 2015 recorded the lowest monthly sales of ₹20,728.35.
A33: 42583 | B33: =SUMIFS('Raw Data'!R:R,'Raw Data'!E:E,">="&A33,'Raw Data'!E:E,"<"&EDATE(A33,1)) -> 46339.988 | X33: Yearly performance: 2017 recorded the highest annual sales among the four years, while 2015 was lower than 2014.
A34: 42614 | B34: =SUMIFS('Raw Data'!R:R,'Raw Data'!E:E,">="&A34,'Raw Data'!E:E,"<"&EDATE(A34,1)) -> 41985.142 | X34: Monthly variation: Sales fluctuate considerably across months, indicating that sales performance is not uniform throughout the year.
A35: 42644 | B35: =SUMIFS('Raw Data'!R:R,'Raw Data'!E:E,">="&A35,'Raw Data'!E:E,"<"&EDATE(A35,1)) -> 52268.15
A36: 42675 | B36: =SUMIFS('Raw Data'!R:R,'Raw Data'!E:E,">="&A36,'Raw Data'!E:E,"<"&EDATE(A36,1)) -> 66837.585
A37: 42705 | B37: =SUMIFS('Raw Data'!R:R,'Raw Data'!E:E,">="&A37,'Raw Data'!E:E,"<"&EDATE(A37,1)) -> 72954.156
A38: 42736 | B38: =SUMIFS('Raw Data'!R:R,'Raw Data'!E:E,">="&A38,'Raw Data'!E:E,"<"&EDATE(A38,1)) -> 64734.311
A39: 42767 | B39: =SUMIFS('Raw Data'!R:R,'Raw Data'!E:E,">="&A39,'Raw Data'!E:E,"<"&EDATE(A39,1)) -> 50011.489
A40: 42795 | B40: =SUMIFS('Raw Data'!R:R,'Raw Data'!E:E,">="&A40,'Raw Data'!E:E,"<"&EDATE(A40,1)) -> 74774.084
A41: 42826 | B41: =SUMIFS('Raw Data'!R:R,'Raw Data'!E:E,">="&A41,'Raw Data'!E:E,"<"&EDATE(A41,1)) -> 39072.002
A42: 42856 | B42: =SUMIFS('Raw Data'!R:R,'Raw Data'!E:E,">="&A42,'Raw Data'!E:E,"<"&EDATE(A42,1)) -> 40882.446
A43: 42887 | B43: =SUMIFS('Raw Data'!R:R,'Raw Data'!E:E,">="&A43,'Raw Data'!E:E,"<"&EDATE(A43,1)) -> 47742.325
A44: 42917 | B44: =SUMIFS('Raw Data'!R:R,'Raw Data'!E:E,">="&A44,'Raw Data'!E:E,"<"&EDATE(A44,1)) -> 54382.087
A45: 42948 | B45: =SUMIFS('Raw Data'!R:R,'Raw Data'!E:E,">="&A45,'Raw Data'!E:E,"<"&EDATE(A45,1)) -> 75675.304
A46: 42979 | B46: =SUMIFS('Raw Data'!R:R,'Raw Data'!E:E,">="&A46,'Raw Data'!E:E,"<"&EDATE(A46,1)) -> 74164.608
... A49: 43070 | B49: =SUMIFS('Raw Data'!R:R,'Raw Data'!E:E,">="&A49,'Raw Data'!E:E,"<"&EDATE(A49,1)) -> 56969.196
